{
  "_class": "symbolInstance",
  "booleanOperation": -1,
  "clippingMaskMode": 0,
  "do_objectID": "AEE8CE93-966C-465F-84AE-8BBE4C92D695",
  "exportOptions": {
    "_class": "exportOptions",
    "do_objectID": "E5DDD8EF-6F53-44DF-A3D8-7E10D6ECE0E7",
    "exportFormats": [
    ],
    "includedLayerIds": [
    ],
    "layerOptions": 0,
    "shouldTrim": false
  },
  "frame": {
    "_class": "rect",
    "constrainProportions": false,
    "do_objectID": "0F9BDACE-6BB7-4033-AF5A-018D195BA585",
    "height": 80,
    "width": 1440,
    "x": 0,
    "y": 0
  },
  "hasClippingMask": false,
  "horizontalSpacing": 0,
  "isFixedToViewport": false,
  "isFlippedHorizontal": false,
  "isFlippedVertical": false,
  "isLocked": false,
  "isVisible": true,
  "layerListExpandedType": 0,
  "name": "Web_header_1",
  "nameIsFixed": false,
  "overrideValues": [
  ],
  "resizingConstraint": 63,
  "resizingType": 0,
  "rotation": 0,
  "scale": 1,
  "shouldBreakMaskChain": false,
  "style": {
    "_class": "style",
    "do_objectID": "8E3F4DD0-5996-42A5-A1CD-A8A5B23C78D0",
    "endMarkerType": 0,
    "miterLimit": 10,
    "startMarkerType": 0,
    "windingRule": 1
  },
  "symbolID": "C3051A2C-1F1D-4FE8-ABF9-F7F33CC7461B",
  "verticalSpacing": 0
}