{
  "_class": "shapePath",
  "booleanOperation": -1,
  "clippingMaskMode": 0,
  "do_objectID": "F15EDAFE-E183-45DD-BA44-796B4C666642",
  "edited": true,
  "exportOptions": {
    "_class": "exportOptions",
    "do_objectID": "623EFE47-B645-4C94-8534-11833F6A6163",
    "exportFormats": [
    ],
    "includedLayerIds": [
    ],
    "layerOptions": 0,
    "shouldTrim": false
  },
  "frame": {
    "_class": "rect",
    "constrainProportions": false,
    "do_objectID": "F722BD90-3CDA-4B9B-BA44-469F80BF34D2",
    "height": 0.265625,
    "width": 0.265625,
    "x": 135.8671874999999,
    "y": 67.86705468750002
  },
  "hasClippingMask": false,
  "isClosed": true,
  "isFixedToViewport": false,
  "isFlippedHorizontal": false,
  "isFlippedVertical": false,
  "isLocked": false,
  "isVisible": true,
  "layerListExpandedType": 0,
  "name": "Path",
  "nameIsFixed": false,
  "pointRadiusBehaviour": 1,
  "points": [
    {
      "_class": "curvePoint",
      "cornerRadius": 0,
      "curveFrom": "{0.5, 0.49950000000001182}",
      "curveMode": 1,
      "curveTo": "{0.5, 0.49950000000001182}",
      "hasCurveFrom": false,
      "hasCurveTo": false,
      "point": "{0.5, 0.49950000000001182}"
    },
    {
      "_class": "curvePoint",
      "cornerRadius": 0,
      "curveFrom": "{0.5, 0.49950000000001182}",
      "curveMode": 1,
      "curveTo": "{0.5, 0.49950000000001182}",
      "hasCurveFrom": false,
      "hasCurveTo": false,
      "point": "{0.5, 0.49950000000001182}"
    },
    {
      "_class": "curvePoint",
      "cornerRadius": 0,
      "curveFrom": "{0.5, 0.50049999999998818}",
      "curveMode": 1,
      "curveTo": "{0.5, 0.50049999999998818}",
      "hasCurveFrom": false,
      "hasCurveTo": false,
      "point": "{0.5, 0.50049999999998818}"
    }
  ],
  "resizingConstraint": 63,
  "resizingType": 0,
  "rotation": 0,
  "shouldBreakMaskChain": false,
  "style": {
    "_class": "style",
    "do_objectID": "CE11CEC3-17F7-4675-8602-BFE444E8AF42",
    "endMarkerType": 0,
    "fills": [
      {
        "_class": "fill",
        "color": {
          "_class": "color",
          "alpha": 1,
          "blue": 0,
          "green": 0,
          "red": 0
        },
        "fillType": 0,
        "isEnabled": true,
        "noiseIndex": 0,
        "noiseIntensity": 0,
        "patternFillType": 1,
        "patternTileScale": 1
      }
    ],
    "miterLimit": 10,
    "startMarkerType": 0,
    "windingRule": 1
  }
}