{
  "_class": "text",
  "attributedString": {
    "_class": "attributedString",
    "attributes": [
      {
        "_class": "stringAttribute",
        "attributes": {
          "MSAttributedStringColorAttribute": {
            "_class": "color",
            "alpha": 1,
            "blue": 0.1882352941176471,
            "green": 0.1882352941176471,
            "red": 0.1882352941176471
          },
          "MSAttributedStringFontAttribute": {
            "_class": "fontDescriptor",
            "attributes": {
              "name": "Montserrat-Regular",
              "size": 14
            }
          },
          "kerning": 0.25,
          "ligature": 0,
          "paragraphStyle": {
            "_class": "paragraphStyle",
            "allowsDefaultTighteningForTruncation": 0,
            "maximumLineHeight": 20,
            "minimumLineHeight": 20
          }
        },
        "length": 65,
        "location": 0
      }
    ],
    "string": "Conoce el correcto uso del GNV  y el deber de los participantes. "
  },
  "automaticallyDrawOnUnderlyingPath": false,
  "booleanOperation": 0,
  "clippingMaskMode": 0,
  "do_objectID": "B2BB7429-224B-4628-BF99-E81DCCF03A5E",
  "dontSynchroniseWithSymbol": false,
  "exportOptions": {
    "_class": "exportOptions",
    "do_objectID": "04687C35-341E-476E-B752-D02899329503",
    "exportFormats": [
    ],
    "includedLayerIds": [
    ],
    "layerOptions": 0,
    "shouldTrim": false
  },
  "frame": {
    "_class": "rect",
    "constrainProportions": false,
    "do_objectID": "0E559C08-A758-43E8-B9B1-94CCB67FF20E",
    "height": 40,
    "width": 349,
    "x": 18,
    "y": 50
  },
  "glyphBounds": "{{0, 4}, {329, 34}}",
  "hasClippingMask": false,
  "isFixedToViewport": false,
  "isFlippedHorizontal": false,
  "isFlippedVertical": false,
  "isLocked": false,
  "isVisible": true,
  "layerListExpandedType": 0,
  "lineSpacingBehaviour": 2,
  "name": "Conoce el correcto u",
  "nameIsFixed": false,
  "resizingConstraint": 2,
  "resizingType": 0,
  "rotation": 0,
  "sharedStyleID": "A19FF0DF-5202-4FA1-B952-F579E3734D4F",
  "shouldBreakMaskChain": false,
  "style": {
    "_class": "style",
    "contextSettings": {
      "_class": "graphicsContextSettings",
      "blendMode": 0,
      "do_objectID": "CA031FFB-4ECA-43EA-BBB6-B3441E5334D6",
      "opacity": 0.87
    },
    "do_objectID": "C44A4C03-D1E5-4072-930A-603EFEB359D9",
    "endMarkerType": 0,
    "miterLimit": 10,
    "startMarkerType": 0,
    "textStyle": {
      "_class": "textStyle",
      "do_objectID": "73F904CC-6EEF-47FB-AC16-97CFD24AB7A8",
      "encodedAttributes": {
        "MSAttributedStringColorAttribute": {
          "_class": "color",
          "alpha": 1,
          "blue": 0.1882352941176471,
          "green": 0.1882352941176471,
          "red": 0.1882352941176471
        },
        "MSAttributedStringFontAttribute": {
          "_class": "fontDescriptor",
          "attributes": {
            "name": "Montserrat-Regular",
            "size": 14
          }
        },
        "kerning": 0.25,
        "ligature": 0,
        "paragraphStyle": {
          "_class": "paragraphStyle",
          "allowsDefaultTighteningForTruncation": 0,
          "maximumLineHeight": 20,
          "minimumLineHeight": 20
        }
      },
      "verticalAlignment": 0
    },
    "windingRule": 1
  },
  "textBehaviour": 1,
  "userInfo": {
    "com.invisionlabs.duplicate": {
      "type-duplicate": {
        "action": "article",
        "options": {
          "section": "philosophy",
          "type": "title"
        },
        "title": "Philosophy"
      }
    }
  }
}