{
  "_class": "shapePath",
  "booleanOperation": -1,
  "clippingMaskMode": 0,
  "do_objectID": "F0AC639D-36DE-4C16-8115-596D52802313",
  "edited": true,
  "exportOptions": {
    "_class": "exportOptions",
    "do_objectID": "E6CD0F63-67C8-4187-AFAF-DC773DDDE4E4",
    "exportFormats": [
    ],
    "includedLayerIds": [
    ],
    "layerOptions": 0,
    "shouldTrim": false
  },
  "frame": {
    "_class": "rect",
    "constrainProportions": false,
    "do_objectID": "02395073-2613-4D19-B6FE-F2D645CFEC82",
    "height": 20.61532175689479,
    "width": 68.51453931149585,
    "x": 6.831934119379889,
    "y": 108.5499489274775
  },
  "hasClippingMask": false,
  "isClosed": true,
  "isFixedToViewport": false,
  "isFlippedHorizontal": false,
  "isFlippedVertical": false,
  "isLocked": false,
  "isVisible": true,
  "layerListExpandedType": 0,
  "name": "Shape",
  "nameIsFixed": false,
  "pointRadiusBehaviour": 0,
  "points": [
    {
      "_class": "curvePoint",
      "cornerRadius": 0,
      "curveFrom": "{0, 0.81805929919137466}",
      "curveMode": 4,
      "curveTo": "{0, 0.91913746630727766}",
      "hasCurveFrom": false,
      "hasCurveTo": true,
      "point": "{0, 0.81805929919137466}"
    },
    {
      "_class": "curvePoint",
      "cornerRadius": 0,
      "curveFrom": "{0, 0}",
      "curveMode": 1,
      "curveTo": "{0, 0}",
      "hasCurveFrom": false,
      "hasCurveTo": false,
      "point": "{0, 0}"
    },
    {
      "_class": "curvePoint",
      "cornerRadius": 0,
      "curveFrom": "{1, 0}",
      "curveMode": 1,
      "curveTo": "{1, 0}",
      "hasCurveFrom": false,
      "hasCurveTo": false,
      "point": "{1, 0}"
    },
    {
      "_class": "curvePoint",
      "cornerRadius": 0,
      "curveFrom": "{1, 0.91778975741239865}",
      "curveMode": 4,
      "curveTo": "{1, 0.81805929919137466}",
      "hasCurveFrom": true,
      "hasCurveTo": false,
      "point": "{1, 0.81805929919137466}"
    },
    {
      "_class": "curvePoint",
      "cornerRadius": 0,
      "curveFrom": "{0.94505494505494503, 1}",
      "curveMode": 4,
      "curveTo": "{0.97557997557997556, 1}",
      "hasCurveFrom": false,
      "hasCurveTo": true,
      "point": "{0.94505494505494503, 1}"
    },
    {
      "_class": "curvePoint",
      "cornerRadius": 0,
      "curveFrom": "{0.024827024827024865, 1}",
      "curveMode": 4,
      "curveTo": "{0.05494505494505484, 1}",
      "hasCurveFrom": true,
      "hasCurveTo": false,
      "point": "{0.05494505494505484, 1}"
    }
  ],
  "resizingConstraint": 63,
  "resizingType": 0,
  "rotation": 0,
  "shouldBreakMaskChain": false,
  "style": {
    "_class": "style",
    "blur": {
      "_class": "blur",
      "center": "{0.5, 0.5}",
      "do_objectID": "B1A9C657-3801-4D93-9EDC-2A8A68C7D34C",
      "isEnabled": false,
      "motionAngle": 0,
      "radius": 2.596348884381339,
      "saturation": 1,
      "type": 0
    },
    "do_objectID": "2E9C7B24-9D82-4069-85A7-83BD38DA20E3",
    "endMarkerType": 0,
    "fills": [
      {
        "_class": "fill",
        "color": {
          "_class": "color",
          "alpha": 1,
          "blue": 0,
          "green": 0,
          "red": 0
        },
        "fillType": 0,
        "isEnabled": true,
        "noiseIndex": 0,
        "noiseIntensity": 0,
        "patternFillType": 1,
        "patternTileScale": 1
      }
    ],
    "miterLimit": 10,
    "startMarkerType": 0,
    "windingRule": 0
  }
}