{
  "_class": "sharedStyle",
  "do_objectID": "5A2F021A-42BA-4471-9B96-0E8B42584584",
  "name": "Caption/Green/Regular - Centered",
  "value": {
    "_class": "style",
    "endMarkerType": 0,
    "miterLimit": 10,
    "startMarkerType": 0,
    "textStyle": {
      "_class": "textStyle",
      "encodedAttributes": {
        "MSAttributedStringColorAttribute": {
          "_class": "color",
          "alpha": 1,
          "blue": 0.2901960784,
          "green": 0.7098039216,
          "red": 0.2235294118
        },
        "MSAttributedStringFontAttribute": {
          "_class": "fontDescriptor",
          "attributes": {
            "name": "Roboto-Regular",
            "size": 12
          }
        },
        "paragraphStyle": {
          "_class": "paragraphStyle",
          "alignment": 0,
          "allowsDefaultTighteningForTruncation": 0,
          "maximumLineHeight": 21,
          "minimumLineHeight": 21
        }
      },
      "verticalAlignment": 0
    },
    "windingRule": 1
  }
}