{
  "_class": "symbolInstance",
  "booleanOperation": 0,
  "clippingMaskMode": 0,
  "do_objectID": "A379DA56-E00B-4C56-8294-B64332F24E7A",
  "exportOptions": {
    "_class": "exportOptions",
    "exportFormats": [
    ],
    "includedLayerIds": [
    ],
    "layerOptions": 0,
    "shouldTrim": false
  },
  "frame": {
    "_class": "rect",
    "constrainProportions": false,
    "height": 16,
    "width": 16,
    "x": 0,
    "y": 0
  },
  "hasClippingMask": false,
  "horizontalSpacing": 0,
  "isFixedToViewport": false,
  "isFlippedHorizontal": false,
  "isFlippedVertical": false,
  "isLocked": false,
  "isVisible": true,
  "layerListExpandedType": 0,
  "name": "Base / Layout",
  "nameIsFixed": true,
  "overrideValues": [
    {
      "_class": "overrideValue",
      "overrideName": "16422103-B84B-4E6E-BF9A-E4B065EC8A7A_symbolID",
      "value": "BB1E849E-14BE-4375-A445-7B3A24C22C86"
    },
    {
      "_class": "overrideValue",
      "overrideName": "3633AC30-3414-4FD5-9E54-D7BD3740230B_symbolID",
      "value": ""
    }
  ],
  "resizingConstraint": 45,
  "resizingType": 0,
  "rotation": 0,
  "scale": 1,
  "shouldBreakMaskChain": false,
  "style": {
    "_class": "style",
    "endMarkerType": 0,
    "miterLimit": 10,
    "startMarkerType": 0,
    "windingRule": 1
  },
  "symbolID": "651982F9-0A76-4701-A445-26402BA8CC8D",
  "verticalSpacing": 0
}