{
  "_class": "text",
  "attributedString": {
    "_class": "attributedString",
    "attributes": [
      {
        "_class": "stringAttribute",
        "attributes": {
          "MSAttributedStringColorAttribute": {
            "_class": "color",
            "alpha": 1,
            "blue": 0.1882352941176471,
            "green": 0.1882352941176471,
            "red": 0.1882352941176471
          },
          "MSAttributedStringFontAttribute": {
            "_class": "fontDescriptor",
            "attributes": {
              "name": "Montserrat-Medium",
              "size": 20
            }
          },
          "ligature": 0,
          "paragraphStyle": {
            "_class": "paragraphStyle",
            "alignment": 3,
            "allowsDefaultTighteningForTruncation": 0
          }
        },
        "length": 168,
        "location": 0
      }
    ],
    "string": "Entidad que administra El Sistema de Control de Carga del GNV\n\nAdministra la información generada por todos los participantes de la cadena comercial del GNV en el Perú."
  },
  "automaticallyDrawOnUnderlyingPath": false,
  "booleanOperation": -1,
  "clippingMaskMode": 0,
  "do_objectID": "190F781B-DB13-45EB-A2BA-9D6177B6BA33",
  "dontSynchroniseWithSymbol": false,
  "exportOptions": {
    "_class": "exportOptions",
    "do_objectID": "BAC22A91-593A-477B-BC2D-37B04A3A8846",
    "exportFormats": [
    ],
    "includedLayerIds": [
    ],
    "layerOptions": 0,
    "shouldTrim": false
  },
  "frame": {
    "_class": "rect",
    "constrainProportions": false,
    "do_objectID": "DE0ECD38-2941-4FE2-BC61-4B1720D55B52",
    "height": 160,
    "width": 406,
    "x": 0,
    "y": 18
  },
  "glyphBounds": "{{-1, 3}, {407, 137}}",
  "hasClippingMask": false,
  "isFixedToViewport": false,
  "isFlippedHorizontal": false,
  "isFlippedVertical": false,
  "isLocked": false,
  "isVisible": true,
  "layerListExpandedType": 0,
  "lineSpacingBehaviour": 2,
  "name": "Entidad que administ",
  "nameIsFixed": false,
  "resizingConstraint": 47,
  "resizingType": 0,
  "rotation": 0,
  "sharedStyleID": "BB37E4CB-176F-44F1-AAF0-061E9D390688",
  "shouldBreakMaskChain": false,
  "style": {
    "_class": "style",
    "do_objectID": "EF7B0A3D-988C-4AC5-8649-9E3FABE01D80",
    "endMarkerType": 0,
    "miterLimit": 10,
    "startMarkerType": 0,
    "textStyle": {
      "_class": "textStyle",
      "do_objectID": "D318D233-BEA2-4A91-9822-0656168D46B2",
      "encodedAttributes": {
        "MSAttributedStringColorAttribute": {
          "_class": "color",
          "alpha": 1,
          "blue": 0.1882352941176471,
          "green": 0.1882352941176471,
          "red": 0.1882352941176471
        },
        "MSAttributedStringFontAttribute": {
          "_class": "fontDescriptor",
          "attributes": {
            "name": "Montserrat-Medium",
            "size": 20
          }
        },
        "ligature": 0,
        "paragraphStyle": {
          "_class": "paragraphStyle",
          "alignment": 3,
          "allowsDefaultTighteningForTruncation": 0
        }
      },
      "verticalAlignment": 0
    },
    "windingRule": 1
  },
  "textBehaviour": 2
}